kmy_mcp_v1_2509/__init__.py
kmy_mcp_v1_2509-0.1.0.dist-info/WHEEL
kmy_mcp_v1_2509-0.1.0.dist-info/entry_points.txt
kmy_mcp_v1_2509-0.1.0.dist-info/METADATA
kmy_mcp_v1_2509-0.1.0.dist-info/RECORD
